[
	{ "name": "Ant", "id": 0, "tier": 1, "packs": [1] },
	{ "name": "Beaver", "id": 3, "tier": 1, "packs": [1,2] },
	{ "name": "Cricket", "id": 17, "tier": 1, "packs": [1] },
	{ "name": "Duck", "id": 26, "tier": 1, "packs": [1,2] },
	{ "name": "Fish", "id": 32, "tier": 1, "packs": [1] },
	{ "name": "Horse", "id": 39, "tier": 1, "packs": [1] },
	{ "name": "Mosquito", "id": 47, "tier": 1, "packs": [1] },
	{ "name": "Otter", "id": 51, "tier": 1, "packs": [1] },
	{ "name": "Pig", "id": 59, "tier": 1, "packs": [1] },
	{ "name": "Pigeon", "id": 559, "tier": 1, "packs": [1] },
	{ "name": "Beetle", "id": 88, "tier": 1, "packs": [2] },
	{ "name": "Bluebird", "id": 89, "tier": 1, "packs": [2] },
	{ "name": "Chinchilla", "id": 161, "tier": 1, "packs": [2] },
	{ "name": "Chipmunk", "id": 184, "tier": 1, "packs": [2,4] },
	{ "name": "Ferret", "id": 172, "tier": 1, "packs": [2] },
	{ "name": "Gecko", "id": 229, "tier": 1, "packs": [2] },
	{ "name": "Ladybug", "id": 92, "tier": 1, "packs": [2] },
	{ "name": "Moth", "id": 141, "tier": 1, "packs": [1] },
	{ "name": "Cockroach", "id": 18, "tier": 1, "packs": [3] },
	{ "name": "Duckling", "id": 113, "tier": 1, "packs": [3] },
	{ "name": "Frog", "id": 139, "tier": 1, "packs": [3] },
	{ "name": "Hummingbird", "id": 138, "tier": 1, "packs": [3] },
	{ "name": "Kiwi", "id": 131, "tier": 1, "packs": [3] },
	{ "name": "Marmoset", "id": 204, "tier": 1, "packs": [1] },
	{ "name": "Mouse", "id": 48, "tier": 1, "packs": [3] },
	{ "name": "Pillbug", "id": 149, "tier": 1, "packs": [3] },
	{ "name": "Frilled Dragon", "id": 198, "tier": 1, "packs": [1] },
	{ "name": "Bulldog", "id": 189, "tier": 1, "packs": [4] },
	{ "name": "Cone Snail", "id": 272, "tier": 1, "packs": [4] },
	{ "name": "Goose", "id": 232, "tier": 1, "packs": [4] },
	{ "name": "Groundhog", "id": 233, "tier": 1, "packs": [4] },
	{ "name": "Magpie", "id": 239, "tier": 1, "packs": [4] },
	{ "name": "Opossum", "id": 187, "tier": 1, "packs": [4] },
	{ "name": "Pied Tamarin", "id": 251, "tier": 1, "packs": [4] },
	{ "name": "Silkmoth", "id": 260, "tier": 1, "packs": [4] },
	{ "name": "Alchemedes", "id": 626, "tier": 1, "packs": [5] },
	{ "name": "Baku", "id": 628, "tier": 1, "packs": [5] },
	{ "name": "Barghest", "id": 621, "tier": 1, "packs": [5] },
	{ "name": "Basilisk", "id": 332, "tier": 1, "packs": [5] },
	{ "name": "Bunyip", "id": 601, "tier": 1, "packs": [5] },
	{ "name": "Cuddle Toad", "id": 611, "tier": 1, "packs": [5] },
	{ "name": "Murmel", "id": 362, "tier": 1, "packs": [5] },
	{ "name": "Sneaky Egg", "id": 617, "tier": 1, "packs": [5] },
	{ "name": "Tsuchinoko", "id": 379, "tier": 1, "packs": [5] },
	{ "name": "Chihuahua", "id": 541, "tier": 1, "packs": [3] },
	{ "name": "Firefly", "id": 548, "tier": 1, "packs": [3] },
	{ "name": "Gibbon", "id": 550, "tier": 1, "packs": [3] },
	{ "name": "Pheasant", "id": 558, "tier": 1, "packs": [3] },
	{ "name": "Termite", "id": 571, "tier": 1, "packs": [3] },
	{ "name": "Bush", "id": 624, "tier": 1, "packs": [5] },
	{ "name": "Pengobble", "id": 627, "tier": 1, "packs": [5] },
	{ "name": "Budgie", "id": 775, "tier": 1, "packs": [1] },
	{ "name": "Farmer Mouse", "id": 693, "tier": 1, "packs": [1] },
	{ "name": "Weevil", "id": 708, "tier": 1, "packs": [1] },
	{ "name": "Umbrella Bird", "id": 746, "tier": 1, "packs": [6] },
	{ "name": "Pygmy Seahorse", "id": 761, "tier": 1, "packs": [6] },
	{ "name": "Silverfish", "id": 566, "tier": 1, "packs": [6] },
	{ "name": "Nudibranch", "id": 757, "tier": 1, "packs": [7] },
	{ "name": "African Wild Dog", "id": 388, "tier": 1, "packs": [8] },
	{ "name": "Bombus Dahlbomii", "id": 401, "tier": 1, "packs": [8] },
	{ "name": "Ethiopian Wolf", "id": 406, "tier": 1, "packs": [8] },
	{ "name": "Fan Mussel", "id": 408, "tier": 1, "packs": [8] },
	{ "name": "Ili Pika", "id": 417, "tier": 1, "packs": [8] },
	{ "name": "Iriomote Cat", "id": 418, "tier": 1, "packs": [8] },
	{ "name": "Malay Tapir", "id": 421, "tier": 1, "packs": [8] },
	{ "name": "Togian Babirusa", "id": 713, "tier": 1, "packs": [8] },
	{ "name": "Tooth Billed Pigeon", "id": 438, "tier": 1, "packs": [8] },
	{ "name": "Volcano Snail", "id": 440, "tier": 1, "packs": [8] },
	{ "name": "Lemming", "id": 555, "tier": 1, "packs": [4] },

	{ "name": "Crab", "id": 16, "tier": 2, "packs": [1] },
	{ "name": "Flamingo", "id": 29, "tier": 2, "packs": [1] },
	{ "name": "Hedgehog", "id": 37, "tier": 2, "packs": [1] },
	{ "name": "Kangaroo", "id": 40, "tier": 2, "packs": [1] },
	{ "name": "Peacock", "id": 54, "tier": 2, "packs": [1] },
	{ "name": "Rat", "id": 57, "tier": 2, "packs": [1] },
	{ "name": "Snail", "id": 72, "tier": 2, "packs": [1] },
	{ "name": "Spider", "id": 74, "tier": 2, "packs": [1] },
	{ "name": "Swan", "id": 76, "tier": 2, "packs": [1] },
	{ "name": "Worm", "id": 82, "tier": 2, "packs": [1] },
	{ "name": "Bat", "id": 87, "tier": 2, "packs": [2] },
	{ "name": "Beluga Sturgeon", "id": 213, "tier": 2, "packs": [2] },
	{ "name": "Dromedary", "id": 104, "tier": 2, "packs": [2] },
	{ "name": "Frigatebird", "id": 137, "tier": 2, "packs": [1] },
	{ "name": "Lemur", "id": 236, "tier": 2, "packs": [2] },
	{ "name": "Mandrill", "id": 405, "tier": 2, "packs": [2] },
	{ "name": "Robin", "id": 255, "tier": 2, "packs": [2] },
	{ "name": "Shrimp", "id": 67, "tier": 2, "packs": [1] },
	{ "name": "Tabby Cat", "id": 99, "tier": 2, "packs": [2] },
	{ "name": "Atlantic Puffin", "id": 132, "tier": 2, "packs": [3] },
	{ "name": "Dove", "id": 24, "tier": 2, "packs": [3] },
	{ "name": "Guinea Pig", "id": 109, "tier": 2, "packs": [3] },
	{ "name": "Iguana", "id": 147, "tier": 2, "packs": [3] },
	{ "name": "Jellyfish", "id": 122, "tier": 2, "packs": [3] },
	{ "name": "Koala", "id": 112, "tier": 2, "packs": [3] },
	{ "name": "Panda", "id": 107, "tier": 2, "packs": [3] },
	{ "name": "Salamander", "id": 164, "tier": 2, "packs": [3] },
	{ "name": "Stork", "id": 136, "tier": 2, "packs": [3] },
	{ "name": "Yak", "id": 163, "tier": 2, "packs": [3] },
	{ "name": "Wombat", "id": 207, "tier": 2, "packs": [1] },
	{ "name": "African Penguin", "id": 210, "tier": 2, "packs": [4] },
	{ "name": "Black Necked Stilt", "id": 215, "tier": 2, "packs": [4] },
	{ "name": "Door Head Ant", "id": 220, "tier": 2, "packs": [4] },
	{ "name": "Hercules Beetle", "id": 234, "tier": 2, "packs": [4] },
	{ "name": "Lizard", "id": 237, "tier": 2, "packs": [4] },
	{ "name": "Sea Turtle", "id": 191, "tier": 2, "packs": [4] },
	{ "name": "Sea Urchin", "id": 258, "tier": 2, "packs": [4] },
	{ "name": "Squid", "id": 177, "tier": 2, "packs": [4] },
	{ "name": "Stoat", "id": 263, "tier": 2, "packs": [4] },
	{ "name": "Bigfoot", "id": 334, "tier": 2, "packs": [5] },
	{ "name": "Chupacabra", "id": 339, "tier": 2, "packs": [5] },
	{ "name": "Drop Bear", "id": 341, "tier": 2, "packs": [5] },
	{ "name": "Frost Wolf", "id": 344, "tier": 2, "packs": [5] },
	{ "name": "Gargoyle", "id": 345, "tier": 2, "packs": [5] },
	{ "name": "Ghost Kitten", "id": 346, "tier": 2, "packs": [5] },
	{ "name": "Golden Beetle", "id": 634, "tier": 2, "packs": [5] },
	{ "name": "Jackalope", "id": 353, "tier": 2, "packs": [5] },
	{ "name": "Mothman", "id": 604, "tier": 2, "packs": [5] },
	{ "name": "Nightcrawler", "id": 605, "tier": 2, "packs": [5] },
	{ "name": "Ogopogo", "id": 639, "tier": 2, "packs": [5] },
	{ "name": "Sphinx", "id": 376, "tier": 2, "packs": [5] },
	{ "name": "Thunderbird", "id": 610, "tier": 2, "packs": [5] },
	{ "name": "Seahorse", "id": 152, "tier": 2, "packs": [3] },
	{ "name": "Bass", "id": 537, "tier": 2, "packs": [3] },
	{ "name": "Dumbo Octopus", "id": 545, "tier": 2, "packs": [3] },
	{ "name": "Warf", "id": 382, "tier": 2, "packs": [5] },
	{ "name": "Wyvern", "id": 385, "tier": 2, "packs": [5] },
	{ "name": "Albino Squirrel", "id": 686, "tier": 2, "packs": [1] },
	{ "name": "Dung Beetle", "id": 721, "tier": 2, "packs": [1] },
	{ "name": "Farmer Chicken", "id": 690, "tier": 2, "packs": [1] },
	{ "name": "Mink", "id": 700, "tier": 2, "packs": [1] },
	{ "name": "Vervet", "id": 707, "tier": 2, "packs": [1] },
	{ "name": "Fruit Fly", "id": 695, "tier": 2, "packs": [6] },
	{ "name": "Pink Robin", "id": 732, "tier": 2, "packs": [6] },
	{ "name": "Shima Enaga", "id": 803, "tier": 2, "packs": [3] },
	{ "name": "Desert Rain Frog", "id": 768, "tier": 2, "packs": [4] },
	{ "name": "Honduran White Bat", "id": 726, "tier": 2, "packs": [4] },
	{ "name": "Giant Squirrel", "id": 800, "tier": 2, "packs": [7] },
	{ "name": "Olm", "id": 725, "tier": 2, "packs": [7] },
	{ "name": "Tadpole", "id": 805, "tier": 2, "packs": [7] },
	{ "name": "Araripe Manakin", "id": 394, "tier": 2, "packs": [8] },
	{ "name": "Darwin's Fox", "id": 404, "tier": 2, "packs": [8] },
	{ "name": "European Mink", "id": 407, "tier": 2, "packs": [8] },
	{ "name": "Proboscis Monkey", "id": 425, "tier": 2, "packs": [8] },
	{ "name": "Pygmy Hog", "id": 427, "tier": 2, "packs": [8] },
	{ "name": "Saker Falcon", "id": 430, "tier": 2, "packs": [8] },
	{ "name": "Saola", "id": 431, "tier": 2, "packs": [8] },
	{ "name": "Taita Shrew", "id": 435, "tier": 2, "packs": [8] },
	{ "name": "Takhi", "id": 715, "tier": 2, "packs": [8] },
	{ "name": "White-Bellied Heron", "id": 441, "tier": 2, "packs": [8] },
	{ "name": "Hermit Crab", "id": 783, "tier": 2, "packs": [4] },
	{ "name": "Amphisbaena", "id": 811, "tier": 2, "packs": [5] },
	{ "name": "Bilby", "id": 758, "tier": 2, "packs": [2] },
	{ "name": "Meerkat", "id": 203, "tier": 2, "packs": [4] },
	{ "name": "Roadrunner", "id": 765, "tier": 2, "packs": [3] },

	{ "name": "Toucan", "id": 151, "tier": 3, "packs": [1] },
	{ "name": "Badger", "id": 2, "tier": 3, "packs": [1] },
	{ "name": "Camel", "id": 10, "tier": 3, "packs": [1] },
	{ "name": "Dodo", "id": 21, "tier": 3, "packs": [1] },
	{ "name": "Dog", "id": 22, "tier": 3, "packs": [1] },
	{ "name": "Dolphin", "id": 23, "tier": 3, "packs": [1] },
	{ "name": "Elephant", "id": 28, "tier": 3, "packs": [1] },
	{ "name": "Giraffe", "id": 33, "tier": 3, "packs": [1] },
	{ "name": "Ox", "id": 52, "tier": 3, "packs": [1] },
	{ "name": "Rabbit", "id": 60, "tier": 3, "packs": [1] },
	{ "name": "Sheep", "id": 68, "tier": 3, "packs": [1] },
	{ "name": "Flying Squirrel", "id": 227, "tier": 3, "packs": [2] },
	{ "name": "Goldfish", "id": 121, "tier": 2, "packs": [1] },
	{ "name": "Hare", "id": 551, "tier": 3, "packs": [2] },
	{ "name": "Hatching Chick", "id": 91, "tier": 3, "packs": [2] },
	{ "name": "Hoopoe Bird", "id": 235, "tier": 3, "packs": [2] },
	{ "name": "Mole", "id": 168, "tier": 3, "packs": [1] },
	{ "name": "Owl", "id": 95, "tier": 3, "packs": [2] },
	{ "name": "Pangolin", "id": 249, "tier": 3, "packs": [2] },
	{ "name": "Puppy", "id": 97, "tier": 3, "packs": [2] },
	{ "name": "Tropical Fish", "id": 100, "tier": 3, "packs": [2] },
	{ "name": "Anteater", "id": 105, "tier": 3, "packs": [3] },
	{ "name": "Capybara", "id": 154, "tier": 3, "packs": [3] },
	{ "name": "Cassowary", "id": 133, "tier": 3, "packs": [3] },
	{ "name": "Eel", "id": 120, "tier": 3, "packs": [3] },
	{ "name": "Leech", "id": 165, "tier": 3, "packs": [3] },
	{ "name": "Okapi", "id": 130, "tier": 3, "packs": [3] },
	{ "name": "Pug", "id": 145, "tier": 3, "packs": [3] },
	{ "name": "Toad", "id": 162, "tier": 3, "packs": [3] },
	{ "name": "Aardvark", "id": 193, "tier": 3, "packs": [1] },
	{ "name": "Bear", "id": 140, "tier": 3, "packs": [1] },
	{ "name": "Emperor Tamarin", "id": 197, "tier": 3, "packs": [1] },
	{ "name": "Porcupine", "id": 169, "tier": 3, "packs": [1] },
	{ "name": "Wasp", "id": 160, "tier": 3, "packs": [1] },
	{ "name": "Baboon", "id": 171, "tier": 3, "packs": [4] },
	{ "name": "Betta Fish", "id": 214, "tier": 3, "packs": [4] },
	{ "name": "Flea", "id": 225, "tier": 3, "packs": [4] },
	{ "name": "Flying Fish", "id": 226, "tier": 3, "packs": [4] },
	{ "name": "FowlBird", "id": 228, "tier": 3, "packs": [4] },
	{ "name": "Musk Ox", "id": 245, "tier": 3, "packs": [4] },
	{ "name": "Osprey", "id": 247, "tier": 3, "packs": [4] },
	{ "name": "Royal Flycatcher", "id": 256, "tier": 3, "packs": [4] },
	{ "name": "Surgeon Fish", "id": 264, "tier": 3, "packs": [4] },
	{ "name": "Weasel", "id": 173, "tier": 3, "packs": [4] },
	{ "name": "Brain Cramp", "id": 349, "tier": 3, "packs": [5] },
	{ "name": "Calgreyhound", "id": 336, "tier": 3, "packs": [5] },
	{ "name": "Deer Lord", "id": 651, "tier": 3, "packs": [5] },
	{ "name": "Foo Dog", "id": 625, "tier": 3, "packs": [5] },
	{ "name": "Fur-Bearing Trout", "id": 653, "tier": 3, "packs": [5] },
	{ "name": "Griffin", "id": 348, "tier": 3, "packs": [5] },
	{ "name": "Mana Hound", "id": 635, "tier": 3, "packs": [5] },
	{ "name": "Mandrake", "id": 357, "tier": 3, "packs": [5] },
	{ "name": "Ouroboros", "id": 364, "tier": 3, "packs": [5] },
	{ "name": "Skeleton Dog", "id": 374, "tier": 3, "packs": [5] },
	{ "name": "Slime", "id": 375, "tier": 3, "packs": [5] },
	{ "name": "Tree", "id": 378, "tier": 3, "packs": [5] },
	{ "name": "Cardinal", "id": 539, "tier": 3, "packs": [3] },
	{ "name": "Tuna", "id": 572, "tier": 3, "packs": [3] },
	{ "name": "Orangutan", "id": 157, "tier": 3, "packs": [3] },
	{ "name": "Axehandle Hound", "id": 377, "tier": 3, "packs": [5] },
	{ "name": "Lucky Cat", "id": 623, "tier": 3, "packs": [5] },
	{ "name": "Tatzelwurm", "id": 654, "tier": 3, "packs": [5] },
	{ "name": "Farmer Pig", "id": 694, "tier": 3, "packs": [1] },
	{ "name": "Pony", "id": 560, "tier": 3, "packs": [1] },
	{ "name": "Quail Chick", "id": 778, "tier": 3, "packs": [1] },
	{ "name": "Quetzalcoatlus", "id": 751, "tier": 3, "packs": [1] },
	{ "name": "Sarcastic Fringehead", "id": 763, "tier": 3, "packs": [1] },
	{ "name": "Sugar Glider", "id": 705, "tier": 3, "packs": [1] },
	{ "name": "Great Potoo", "id": 697, "tier": 3, "packs": [6] },
	{ "name": "Dimetrodon", "id": 543, "tier": 3, "packs": [6] },
	{ "name": "Queen Bee", "id": 703, "tier": 3, "packs": [6] },
	{ "name": "Sage-Grouse", "id": 531, "tier": 3, "packs": [3] },
	{ "name": "Blue Dragon", "id": 728, "tier": 3, "packs": [4,5] },
	{ "name": "Jewel Caterpillar", "id": 736, "tier": 3, "packs": [4] },
	{ "name": "Patagonian Mara", "id": 733, "tier": 3, "packs": [4] },
	{ "name": "Caladrius", "id": 786, "tier": 3, "packs": [5] },
	{ "name": "Barnacle", "id": 796, "tier": 3, "packs": [7] },
	{ "name": "Centipede", "id": 540, "tier": 3, "packs": [7] },
	{ "name": "Gerenuk", "id": 740, "tier": 3, "packs": [7] },
	{ "name": "Amami Rabbit", "id": 389, "tier": 3, "packs": [8] },
	{ "name": "Blue-Throated Macaw", "id": 400, "tier": 3, "packs": [8] },
	{ "name": "Hirola", "id": 717, "tier": 3, "packs": [8] },
	{ "name": "Monkey-Faced Bat", "id": 422, "tier": 3, "packs": [8] },
	{ "name": "Pygmy Hippo", "id": 426, "tier": 3, "packs": [8] },
	{ "name": "Roloway Monkey", "id": 429, "tier": 3, "packs": [8] },
	{ "name": "Spoon-Billed Sandpiper", "id": 433, "tier": 3, "packs": [8] },
	{ "name": "Takin", "id": 719, "tier": 3, "packs": [8] },
	{ "name": "Tree Kangaroo", "id": 534, "tier": 3, "packs": [8] },
	{ "name": "Tucuxi", "id": 439, "tier": 3, "packs": [8] },

	{ "name": "Gazelle", "id": 185, "tier": 4, "packs": [4] },
	{ "name": "Bison", "id": 5, "tier": 4, "packs": [1] },
	{ "name": "Blowfish", "id": 7, "tier": 4, "packs": [1] },
	{ "name": "Deer", "id": 20, "tier": 4, "packs": [1] },
	{ "name": "Hippo", "id": 38, "tier": 4, "packs": [1] },
	{ "name": "Parrot", "id": 53, "tier": 4, "packs": [1] },
	{ "name": "Penguin", "id": 56, "tier": 4, "packs": [1] },
	{ "name": "Skunk", "id": 70, "tier": 4, "packs": [1] },
	{ "name": "Squirrel", "id": 75, "tier": 4, "packs": [1] },
	{ "name": "Turtle", "id": 80, "tier": 4, "packs": [1] },
	{ "name": "Whale", "id": 81, "tier": 4, "packs": [1] },
	{ "name": "Buffalo", "id": 8, "tier": 4, "packs": [1] },
	{ "name": "Caterpillar", "id": 12, "tier": 4, "packs": [2] },
	{ "name": "Chameleon", "id": 216, "tier": 4, "packs": [2] },
	{ "name": "Doberman", "id": 273, "tier": 4, "packs": [1] },
	{ "name": "Gharial", "id": 231, "tier": 4, "packs": [2] },
	{ "name": "Llama", "id": 44, "tier": 4, "packs": [2] },
	{ "name": "Lobster", "id": 93, "tier": 4, "packs": [2] },
	{ "name": "Microbe", "id": 94, "tier": 4, "packs": [2] },
	{ "name": "Tahr", "id": 393, "tier": 4, "packs": [2] },
	{ "name": "Whale Shark", "id": 267, "tier": 4, "packs": [2] },
	{ "name": "Clownfish", "id": 117, "tier": 4, "packs": [3] },
	{ "name": "Crow", "id": 195, "tier": 4, "packs": [3] },
	{ "name": "Donkey", "id": 111, "tier": 4, "packs": [3] },
	{ "name": "Hawk", "id": 127, "tier": 4, "packs": [3] },
	{ "name": "Platypus", "id": 159, "tier": 4, "packs": [3] },
	{ "name": "PrayingMantis", "id": 126, "tier": 4, "packs": [3] },
	{ "name": "Jerboa", "id": 199, "tier": 4, "packs": [1] },
	{ "name": "Lynx", "id": 200, "tier": 4, "packs": [1] },
	{ "name": "Seagull", "id": 128, "tier": 4, "packs": [1] },
	{ "name": "Cockatoo", "id": 218, "tier": 4, "packs": [4] },
	{ "name": "Cuttlefish", "id": 176, "tier": 4, "packs": [4] },
	{ "name": "Falcon", "id": 224, "tier": 4, "packs": [4] },
	{ "name": "Manatee", "id": 192, "tier": 4, "packs": [4] },
	{ "name": "Manta Ray", "id": 240, "tier": 4, "packs": [4] },
	{ "name": "Poison Dart Frog", "id": 252, "tier": 4, "packs": [4] },
	{ "name": "Saiga Antelope", "id": 257, "tier": 4, "packs": [4] },
	{ "name": "Sealion", "id": 175, "tier": 4, "packs": [4] },
	{ "name": "Slug", "id": 262, "tier": 4, "packs": [4] },
	{ "name": "Vaquita", "id": 265, "tier": 4, "packs": [4] },
	{ "name": "Abomination", "id": 373, "tier": 4, "packs": [5] },
	{ "name": "Anubis", "id": 331, "tier": 4, "packs": [5] },
	{ "name": "Chimera", "id": 338, "tier": 4, "packs": [5] },
	{ "name": "Cyclops", "id": 630, "tier": 4, "packs": [5] },
	{ "name": "Fairy", "id": 342, "tier": 4, "packs": [5] },
	{ "name": "Kraken", "id": 355, "tier": 4, "packs": [5] },
	{ "name": "Old Mouse", "id": 612, "tier": 4, "packs": [5] },
	{ "name": "Roc", "id": 369, "tier": 4, "packs": [5] },
	{ "name": "Rootling", "id": 622, "tier": 4, "packs": [5] },
	{ "name": "Tiger Bug", "id": 330, "tier": 4, "packs": [5] },
	{ "name": "Visitor", "id": 386, "tier": 4, "packs": [5] },
	{ "name": "Worm Of Sand", "id": 371, "tier": 4, "packs": [5] },
	{ "name": "Unicorn", "id": 380, "tier": 4, "packs": [5] },
	{ "name": "Elk", "id": 546, "tier": 4, "packs": [3] },
	{ "name": "Fairy Armadillo", "id": 547, "tier": 4, "packs": [3] },
	{ "name": "Fossa", "id": 549, "tier": 4, "packs": [3] },
	{ "name": "Sea Anemone", "id": 563, "tier": 4, "packs": [3] },
	{ "name": "Siamese", "id": 565, "tier": 4, "packs": [3] },
	{ "name": "Sparrow", "id": 567, "tier": 4, "packs": [3] },
	{ "name": "Minotaur", "id": 360, "tier": 4, "packs": [4] },
	{ "name": "Pegasus", "id": 365, "tier": 4, "packs": [5] },
	{ "name": "Tandgnost", "id": 607, "tier": 4, "packs": [5] },
	{ "name": "Tandgrisner", "id": 608, "tier": 4, "packs": [5] },
	{ "name": "Andrewsarchus", "id": 730, "tier": 4, "packs": [1] },
	{ "name": "Cuckoo", "id": 787, "tier": 4, "packs":[1] },
	{ "name": "Farmer Cat", "id": 689, "tier": 4, "packs": [1] },
	{ "name": "Gelada", "id": 696, "tier": 4, "packs": [1] },
	{ "name": "Locust", "id": 698, "tier": 4, "packs": [1] },
	{ "name": "Goblin Shark", "id": 754, "tier": 4, "packs": [6] },
	{ "name": "Leafy Sea Dragon", "id": 723, "tier": 4, "packs": [6] },
	{ "name": "Tardigrade", "id": 570, "tier": 4, "packs": [6] },
	{ "name": "Trout", "id": 706, "tier": 4, "packs": [1] },
	{ "name": "Mimic", "id": 359, "tier": 4, "packs": [5] },
	{ "name": "Spider Crab", "id": 727, "tier": 4, "packs": [6] },
	{ "name": "Bloodhound", "id": 797, "tier": 4, "packs": [7] },
	{ "name": "Red Lipped Batfish", "id": 742, "tier": 4, "packs": [7] },
	{ "name": "Spiny Bush Viper", "id": 804, "tier": 4, "packs": [7] },
	{ "name": "Hoatzin", "id": 755, "tier": 4, "packs": [3] },
	{ "name": "Racket Tail", "id": 760, "tier": 4, "packs": [3] },
	{ "name": "Ruspoli's Turaco", "id": 802, "tier": 4, "packs": [3] },
	{ "name": "Blue-Footed Booby", "id": 530, "tier": 4, "packs": [4] },
	{ "name": "Platybelodon", "id": 734, "tier": 4, "packs": [4] },
	{ "name": "Ahuizotl", "id": 785, "tier": 4, "packs": [5] },
	{ "name": "Amazon River Dolphin", "id": 390, "tier": 4, "packs": [8] },
	{ "name": "Angelshark", "id": 392, "tier": 4, "packs": [8] },
	{ "name": "Bonobo", "id": 402, "tier": 4, "packs": [8] },
	{ "name": "Giant Otter", "id": 410, "tier": 4, "packs": [8] },
	{ "name": "Giant Tortoise", "id": 412, "tier": 4, "packs": [8] },
	{ "name": "Golden Tamarin", "id": 720, "tier": 4, "packs": [8] },
	{ "name": "Humphead Wrasse", "id": 416, "tier": 4, "packs": [8] },
	{ "name": "Kakapo", "id": 419, "tier": 4, "packs": [8] },
	{ "name": "Longcomb Sawfish", "id": 420, "tier": 4, "packs": [8] },
	{ "name": "Tasmanian Devil", "id": 437, "tier": 4, "packs": [8] },

	{ "name": "Secretary Bird", "id": 259, "tier": 5, "packs": [4] },
	{ "name": "Armadillo", "id": 166, "tier": 5, "packs": [1] },
	{ "name": "Cow", "id": 15, "tier": 5, "packs": [1] },
	{ "name": "Crocodile", "id": 19, "tier": 5, "packs": [1] },
	{ "name": "Monkey", "id": 46, "tier": 5, "packs": [1] },
	{ "name": "Rhino", "id": 55, "tier": 5, "packs": [1] },
	{ "name": "Rooster", "id": 63, "tier": 5, "packs": [1] },
	{ "name": "Scorpion", "id": 65, "tier": 5, "packs": [1] },
	{ "name": "Seal", "id": 66, "tier": 5, "packs": [1] },
	{ "name": "Shark", "id": 69, "tier": 5, "packs": [1] },
	{ "name": "Turkey", "id": 79, "tier": 5, "packs": [1] },
	{ "name": "Axolotl", "id": 212, "tier": 5, "packs": [2] },
	{ "name": "Chicken", "id": 14, "tier": 5, "packs": [2] },
	{ "name": "Eagle", "id": 27, "tier": 5, "packs": [2] },
	{ "name": "Goat", "id": 34, "tier": 5, "packs": [2] },
	{ "name": "Mosasaurus", "id": 242, "tier": 5, "packs": [2] },
	{ "name": "Panther", "id": 250, "tier": 5, "packs": [2] },
	{ "name": "Snapping Turtle", "id": 277, "tier": 5, "packs": [2] },
	{ "name": "Sting Ray", "id": 178, "tier": 5, "packs": [2] },
	{ "name": "Stonefish", "id": 278, "tier": 5, "packs": [2] },
	{ "name": "Fox", "id": 106, "tier": 5, "packs": [3] },
	{ "name": "Hamster", "id": 110, "tier": 5, "packs": [3] },
	{ "name": "Polar Bear", "id": 108, "tier": 5, "packs": [3] },
	{ "name": "Shoebill", "id": 134, "tier": 5, "packs": [3] },
	{ "name": "Siberian Husky", "id": 146, "tier": 5, "packs": [3] },
	{ "name": "Swordfish", "id": 119, "tier": 5, "packs": [3] },
	{ "name": "Triceratops", "id": 142, "tier": 5, "packs": [3] },
	{ "name": "Vulture", "id": 135, "tier": 5, "packs": [3] },
	{ "name": "Zebra", "id": 155, "tier": 5, "packs": [3] },
	{ "name": "Hyena", "id": 167, "tier": 5, "packs": [1] },
	{ "name": "Moose", "id": 202, "tier": 5, "packs": [1] },
	{ "name": "Raccoon", "id": 158, "tier": 5, "packs": [1] },
	{ "name": "Beluga Whale", "id": 182, "tier": 5, "packs": [4] },
	{ "name": "Blue Ringed Octopus", "id": 271, "tier": 5, "packs": [4] },
	{ "name": "Crane", "id": 219, "tier": 5, "packs": [4] },
	{ "name": "Egyptian Vulture", "id": 221, "tier": 5, "packs": [4] },
	{ "name": "Emu", "id": 223, "tier": 5, "packs": [4] },
	{ "name": "Fire Ant", "id": 274, "tier": 5, "packs": [4] },
	{ "name": "Macaque", "id": 238, "tier": 5, "packs": [4] },
	{ "name": "Nurse Shark", "id": 276, "tier": 5, "packs": [4] },
	{ "name": "Nyala", "id": 246, "tier": 5, "packs": [4] },
	{ "name": "Silver Fox", "id": 261, "tier": 5, "packs": [4] },
	{ "name": "Wolf", "id": 170, "tier": 5, "packs": [4] },
	{ "name": "Bad Dog", "id": 613, "tier": 5, "packs": [5] },
	{ "name": "Boitata", "id": 656, "tier": 5, "packs": [5] },
	{ "name": "Kappa", "id": 655, "tier": 5, "packs": [5] },
	{ "name": "Kitsune", "id": 354, "tier": 5, "packs": [5] },
	{ "name": "Loveland Frogman", "id": 640, "tier": 5, "packs": [5] },
	{ "name": "Nessie", "id": 363, "tier": 5, "packs": [5] },
	{ "name": "Nurikabe", "id": 657, "tier": 5, "packs": [5] },
	{ "name": "Pixiu", "id": 619, "tier": 5, "packs": [5] },
	{ "name": "Red Dragon", "id": 368, "tier": 5, "packs": [5] },
	{ "name": "Salmon Of Knowledge", "id": 370, "tier": 5, "packs": [5] },
	{ "name": "Werewolf", "id": 383, "tier": 5, "packs": [5] },
	{ "name": "Vampire Bat", "id": 381, "tier": 5, "packs": [5] },
	{ "name": "Starfish", "id": 153, "tier": 5, "packs": [3] },
	{ "name": "Ibex", "id": 553, "tier": 5, "packs": [3] },
	{ "name": "Pelican", "id": 129, "tier": 5, "packs": [3] },
	{ "name": "Woodpecker", "id": 156, "tier": 5, "packs": [3] },
	{ "name": "Blobfish", "id": 150, "tier": 5, "packs": [3] },
	{ "name": "Amalgamation", "id": 631, "tier": 5, "packs": [5] },
	{ "name": "Orchid Mantis", "id": 557, "tier": 5, "packs": [2] },
	{ "name": "Dragonfly", "id": 196, "tier": 5, "packs": [1] },
	{ "name": "Hippocampus", "id": 350, "tier": 5, "packs": [5] },
	{ "name": "Maltese", "id": 556, "tier": 5, "packs": [4] },
	{ "name": "Namazu", "id": 784, "tier": 5, "packs": [5] },
	{ "name": "Blue Jay", "id": 774, "tier": 5, "packs": [1] },
	{ "name": "Farmer Crow", "id": 691, "tier": 5, "packs": [1] },
	{ "name": "Flounder", "id": 776, "tier": 5, "packs": [1] },
	{ "name": "Jackal", "id": 554, "tier": 5, "packs": [6] },
	{ "name": "Tarantula Hawk", "id": 569, "tier": 5, "packs": [1] },
	{ "name": "Brahma Chicken", "id": 688, "tier": 5, "packs": [6] },
	{ "name": "Venus Fly Trap", "id": 573, "tier": 5, "packs": [1] },
	{ "name": "Giant Isopod", "id": 752, "tier": 5, "packs": [4] },
	{ "name": "Lusca", "id": 808, "tier": 5, "packs": [5] },
	{ "name": "Pacific Fanfish", "id": 801, "tier": 5, "packs": [7] },
	{ "name": "Sea Cucumber", "id": 564, "tier": 5, "packs": [7] },
	{ "name": "Aye-aye", "id": 395, "tier": 5, "packs": [8] },
	{ "name": "Banggai Cardinalfish", "id": 396, "tier": 5, "packs": [8] },
	{ "name": "Geometric Tortoise", "id": 409, "tier": 5, "packs": [8] },
	{ "name": "Giant Pangasius", "id": 411, "tier": 5, "packs": [8] },
	{ "name": "Hawaiian Monk Seal", "id": 414, "tier": 5, "packs": [8] },
	{ "name": "Marine Iguana", "id": 532, "tier": 5, "packs": [8] },
	{ "name": "Painted Terrapin", "id": 423, "tier": 5, "packs": [8] },
	{ "name": "Red Panda", "id": 428, "tier": 5, "packs": [8] },
	{ "name": "Snow Leopard", "id": 716, "tier": 5, "packs": [8] },
	{ "name": "Taita Thrush", "id": 436, "tier": 5, "packs": [8] },

	{ "name": "Boar", "id": 103, "tier": 6, "packs": [1] },
	{ "name": "Cat", "id": 11, "tier": 6, "packs": [1] },
	{ "name": "Dragon", "id": 25, "tier": 6, "packs": [1] },
	{ "name": "Fly", "id": 30, "tier": 6, "packs": [1] },
	{ "name": "Gorilla", "id": 36, "tier": 6, "packs": [1] },
	{ "name": "Leopard", "id": 41, "tier": 6, "packs": [1] },
	{ "name": "Mammoth", "id": 45, "tier": 6, "packs": [1] },
	{ "name": "Snake", "id": 73, "tier": 6, "packs": [1] },
	{ "name": "Tiger", "id": 77, "tier": 6, "packs": [1] },
	{ "name": "Wolverine", "id": 269, "tier": 6, "packs": [1] },
	{ "name": "Anglerfish", "id": 180, "tier": 6, "packs": [2] },
	{ "name": "Elephant Seal", "id": 222, "tier": 6, "packs": [2] },
	{ "name": "Lionfish", "id": 201, "tier": 6, "packs": [1] },
	{ "name": "Mantis Shrimp", "id": 190, "tier": 6, "packs": [2] },
	{ "name": "Mongoose", "id": 241, "tier": 6, "packs": [2] },
	{ "name": "Octopus", "id": 50, "tier": 6, "packs": [2] },
	{ "name": "Puma", "id": 254, "tier": 6, "packs": [2] },
	{ "name": "Sauropod", "id": 98, "tier": 6, "packs": [2] },
	{ "name": "Tyrannosaurus", "id": 78, "tier": 6, "packs": [2] },
	{ "name": "Hammer Shark", "id": 123, "tier": 6, "packs": [3] },
	{ "name": "Komodo", "id": 124, "tier": 6, "packs": [3] },
	{ "name": "Orca", "id": 116, "tier": 6, "packs": [3] },
	{ "name": "Ostrich", "id": 125, "tier": 6, "packs": [3] },
	{ "name": "Piranha", "id": 118, "tier": 6, "packs": [3] },
	{ "name": "Reindeer", "id": 205, "tier": 6, "packs": [3] },
	{ "name": "Sabertooth", "id": 148, "tier": 6, "packs": [3] },
	{ "name": "Spinosaurus", "id": 143, "tier": 6, "packs": [3] },
	{ "name": "Stegosaurus", "id": 144, "tier": 6, "packs": [3] },
	{ "name": "Velociraptor", "id": 115, "tier": 6, "packs": [3] },
	{ "name": "Lioness", "id": 114, "tier": 6, "packs": [1] },
	{ "name": "Tapir", "id": 208, "tier": 6, "packs": [1] },
	{ "name": "Walrus", "id": 209, "tier": 6, "packs": [1] },
	{ "name": "White Tiger", "id": 206, "tier": 6, "packs": [1] },
	{ "name": "Bird Of Paradise", "id": 181, "tier": 6, "packs": [4] },
	{ "name": "Catfish", "id": 174, "tier": 6, "packs": [4] },
	{ "name": "Cobra", "id": 217, "tier": 6, "packs": [4] },
	{ "name": "German Shepherd", "id": 230, "tier": 6, "packs": [4] },
	{ "name": "Grizzly Bear", "id": 275, "tier": 6, "packs": [4] },
	{ "name": "Highland Cow", "id": 186, "tier": 6, "packs": [4] },
	{ "name": "Oyster", "id": 248, "tier": 6, "packs": [4] },
	{ "name": "Pteranodon", "id": 253, "tier": 6, "packs": [4] },
	{ "name": "Warthog", "id": 266, "tier": 6, "packs": [4] },
	{ "name": "Wildebeest", "id": 268, "tier": 6, "packs": [4] },
	{ "name": "Behemoth", "id": 333, "tier": 6, "packs": [5] },
	{ "name": "Cerberus", "id": 337, "tier": 6, "packs": [5] },
	{ "name": "Cockatrice", "id": 340, "tier": 6, "packs": [5] },
	{ "name": "Hydra", "id": 352, "tier": 6, "packs": [5] },
	{ "name": "Leviathan", "id": 356, "tier": 6, "packs": [5] },
	{ "name": "Manticore", "id": 358, "tier": 6, "packs": [5] },
	{ "name": "Phoenix", "id": 366, "tier": 6, "packs": [5] },
	{ "name": "Questing Beast", "id": 616, "tier": 6, "packs": [5] },
	{ "name": "Quetzalcoatl", "id": 367, "tier": 6, "packs": [5] },
	{ "name": "Sea Serpent", "id": 372, "tier": 6, "packs": [5] },
	{ "name": "Sleipnir", "id": 606, "tier": 6, "packs": [5] },
	{ "name": "Team Spirit", "id": 636, "tier": 6, "packs": [5] },
	{ "name": "Yeti", "id": 387, "tier": 6, "packs": [5] },
	{ "name": "Albatross", "id": 535, "tier": 6 , "packs": [1] },
	{ "name": "Harpy Eagle", "id": 552, "tier": 6, "packs": [1] },
	{ "name": "Ammonite", "id": 536, "tier": 6, "packs": [3] },
	{ "name": "Real Velociraptor", "id": 561, "tier": 6, "packs": [3] },
	{ "name": "Alpaca", "id": 194, "tier": 6, "packs": [1] },
	{ "name": "Small One", "id": 773, "tier": 6, "packs": [5] },
	{ "name": "Jersey Devil", "id": 652, "tier": 6, "packs": [5] },
	{ "name": "Poodle", "id": 96, "tier": 6, "packs": [2] },
	{ "name": "Black Bear", "id": 687, "tier": 6, "packs": [1] },
	{ "name": "Chimpanzee", "id": 542, "tier": 6, "packs": [1] },
	{ "name": "Coconut Crab", "id": 779, "tier": 6, "packs": [1] },
	{ "name": "Eagle Owl", "id": 781, "tier": 6, "packs": [1] },
	{ "name": "Farmer Dog", "id": 692, "tier": 6, "packs": [1] },
	{ "name": "Lamprey", "id": 749, "tier": 6, "packs": [1] },
	{ "name": "Amargasaurus", "id": 772, "tier": 6, "packs": [6] },
	{ "name": "Yellow Boxfish", "id": 766, "tier": 6, "packs": [6] },
	{ "name": "Lion", "id": 42, "tier": 6, "packs": [3] },
	{ "name": "Terror Bird", "id": 806, "tier": 6, "packs": [3] },
	{ "name": "Therizinosaurus", "id": 759, "tier": 6, "packs": [3] },
	{ "name": "Markhor", "id": 743, "tier": 6, "packs": [4] },
	{ "name": "Rockhopper Penguin", "id": 533, "tier": 6, "packs": [4] },
	{ "name": "Akhlut", "id": 782, "tier": 6, "packs": [5] },
	{ "name": "Bakunawa", "id": 603, "tier": 6, "packs": [5] },
	{ "name": "Winter Spirit", "id": 633, "tier": 6, "packs": [5] },
	{ "name": "Sunfish", "id": 568, "tier": 6, "packs": [7] },
	{ "name": "Amsterdam Albatross", "id": 391, "tier": 6, "packs": [8] },
	{ "name": "Bay Cat", "id": 397, "tier": 6, "packs": [8] },
	{ "name": "Black Rhino", "id": 398, "tier": 6, "packs": [8] },
	{ "name": "Blue Whale", "id": 399, "tier": 6, "packs": [8] },
	{ "name": "California Condor", "id": 403, "tier": 6, "packs": [8] },
	{ "name": "Green Sea Turtle", "id": 413, "tier": 6, "packs": [8] },
	{ "name": "Helmeted Hornbill", "id": 415, "tier": 6, "packs": [8] },
	{ "name": "Philippine Eagle", "id": 424, "tier": 6, "packs": [8] },
	{ "name": "Silky Sifaka", "id": 432, "tier": 6, "packs": [8] },
	{ "name": "Sumatran Tiger", "id": 434, "tier": 6, "packs": [8] },
	{ "name": "Hooded Seal", "id": 753, "tier": 6, "packs": [8] }
]
